{
  "posts": [
    {
      "name": "Sidhant",
      "region": "uk",
      "modifidedBy": "ss",
      "modifiedOn": "ss",
      "formArray": [],
      "templateId": "ssss",
      "id": 7
    },
    {
      "name": "ss",
      "region": "uk",
      "modifidedBy": "2024-03-23",
      "modifiedOn": "2024-04-01",
      "formArray": [],
      "templateId": "ssss",
      "id": 8
    }
  ],
  "signUpUsers": [
    {
      "userName": "s",
      "email": "s",
      "password": "s",
      "id": 1
    }
  ],
  "comments": [],
  "profile": {
    "name": "typicode"
  }
}